cli/__init__.py
cli/main.py
cli/ECCV2022-RIFE/.gitignore
cli/ECCV2022-RIFE/Colab_demo.ipynb
cli/ECCV2022-RIFE/LICENSE
cli/ECCV2022-RIFE/README.md
cli/ECCV2022-RIFE/dataset.py
cli/ECCV2022-RIFE/inference_img.py
cli/ECCV2022-RIFE/inference_video.py
cli/ECCV2022-RIFE/requirements.txt
cli/ECCV2022-RIFE/train.py
cli/ECCV2022-RIFE/.git/HEAD
cli/ECCV2022-RIFE/.git/config
cli/ECCV2022-RIFE/.git/description
cli/ECCV2022-RIFE/.git/index
cli/ECCV2022-RIFE/.git/packed-refs
cli/ECCV2022-RIFE/.git/hooks/applypatch-msg.sample
cli/ECCV2022-RIFE/.git/hooks/commit-msg.sample
cli/ECCV2022-RIFE/.git/hooks/fsmonitor-watchman.sample
cli/ECCV2022-RIFE/.git/hooks/post-update.sample
cli/ECCV2022-RIFE/.git/hooks/pre-applypatch.sample
cli/ECCV2022-RIFE/.git/hooks/pre-commit.sample
cli/ECCV2022-RIFE/.git/hooks/pre-merge-commit.sample
cli/ECCV2022-RIFE/.git/hooks/pre-push.sample
cli/ECCV2022-RIFE/.git/hooks/pre-rebase.sample
cli/ECCV2022-RIFE/.git/hooks/pre-receive.sample
cli/ECCV2022-RIFE/.git/hooks/prepare-commit-msg.sample
cli/ECCV2022-RIFE/.git/hooks/push-to-checkout.sample
cli/ECCV2022-RIFE/.git/hooks/sendemail-validate.sample
cli/ECCV2022-RIFE/.git/hooks/update.sample
cli/ECCV2022-RIFE/.git/info/exclude
cli/ECCV2022-RIFE/.git/logs/HEAD
cli/ECCV2022-RIFE/.git/logs/refs/heads/main
cli/ECCV2022-RIFE/.git/logs/refs/remotes/origin/HEAD
cli/ECCV2022-RIFE/.git/objects/pack/pack-6b4c3777946824fb1b1a94beff6e85a0d848464a.idx
cli/ECCV2022-RIFE/.git/objects/pack/pack-6b4c3777946824fb1b1a94beff6e85a0d848464a.pack
cli/ECCV2022-RIFE/.git/objects/pack/pack-6b4c3777946824fb1b1a94beff6e85a0d848464a.rev
cli/ECCV2022-RIFE/.git/refs/heads/main
cli/ECCV2022-RIFE/.git/refs/remotes/origin/HEAD
cli/ECCV2022-RIFE/benchmark/ATD12K.py
cli/ECCV2022-RIFE/benchmark/HD.py
cli/ECCV2022-RIFE/benchmark/HD_multi_4X.py
cli/ECCV2022-RIFE/benchmark/MiddleBury_Other.py
cli/ECCV2022-RIFE/benchmark/UCF101.py
cli/ECCV2022-RIFE/benchmark/Vimeo90K.py
cli/ECCV2022-RIFE/benchmark/testtime.py
rifex-0.1.1.dist-info/LICENSE
rifex-0.1.1.dist-info/METADATA
rifex-0.1.1.dist-info/WHEEL
rifex-0.1.1.dist-info/entry_points.txt
rifex-0.1.1.dist-info/top_level.txt
rifex-0.1.1.dist-info/RECORD
