Metadata-Version: 2.1
Name: rifex
Version: 0.1.1
Summary: A CLI tool for video frame interpolation using RIFE
Author: dumgum82
Author-email: dumgum42@example.com
Classifier: Programming Language :: Python :: 3
Classifier: License :: OSI Approved :: MIT License
Classifier: Operating System :: OS Independent
Requires-Python: >=3.6
License-File: LICENSE
Requires-Dist: ffmpeg-python
Requires-Dist: Pillow
